etl/__init__.py
etl/data_cleanup.py
etl/data_processing.py
etl/db_util.py
etl/decorators.py
etl/logging.py
etl/requests_util.py
etl/secrets.py
etl/sources.py
fjelltopp_etl-0.0.7.dist-info/LICENSE.txt
fjelltopp_etl-0.0.7.dist-info/METADATA
fjelltopp_etl-0.0.7.dist-info/WHEEL
fjelltopp_etl-0.0.7.dist-info/top_level.txt
fjelltopp_etl-0.0.7.dist-info/RECORD
