Metadata-Version: 2.1
Name: fjelltopp-etl
Version: 0.0.7
Summary: UNKNOWN
Home-page: https://github.com/fjelltopp/fjelltopp-etl
Author: Tomek Sabała
Author-email: tomek@fjelltopp.org
License: UNKNOWN
Keywords: etl,dataprocessing,pandas
Platform: UNKNOWN
Classifier: Development Status :: 3 - Alpha
Classifier: Intended Audience :: Developers
Classifier: Topic :: Software Development :: Build Tools
Classifier: License :: OSI Approved :: MIT License
Classifier: Programming Language :: Python :: 3
Classifier: Programming Language :: Python :: 3.4
Classifier: Programming Language :: Python :: 3.5
Classifier: Programming Language :: Python :: 3.6
License-File: LICENSE.txt
Requires-Dist: boto3 (==1.20.45)
Requires-Dist: botocore (==1.23.45)
Requires-Dist: certifi (==2021.10.8)
Requires-Dist: chardet (==4.0.0)
Requires-Dist: docutils (==0.18.1)
Requires-Dist: idna (==3.3)
Requires-Dist: jmespath (==0.10.0)
Requires-Dist: numpy (==1.22.1)
Requires-Dist: pandas (==1.4.0)
Requires-Dist: python-dateutil (==2.8.2)
Requires-Dist: python-slugify (==5.0.2)
Requires-Dist: pytz (==2021.3)
Requires-Dist: requests (==2.27.1)
Requires-Dist: s3transfer (==0.5.0)
Requires-Dist: six (==1.16.0)
Requires-Dist: SQLAlchemy (==1.4.31)
Requires-Dist: text-unidecode (==1.3)
Requires-Dist: urllib3 (==1.26.8)
Requires-Dist: watchtower (==3.0.0)
Requires-Dist: xmltodict (==0.12.0)
